tranquilizer/__init__.py
tranquilizer/__main__.py
tranquilizer/_version.py
tranquilizer/application.py
tranquilizer/decorator.py
tranquilizer/handler.py
tranquilizer/main.py
tranquilizer/resource.py
tranquilizer/types.py
tranquilizer-0.9.2.dist-info/LICENSE
tranquilizer-0.9.2.dist-info/METADATA
tranquilizer-0.9.2.dist-info/WHEEL
tranquilizer-0.9.2.dist-info/entry_points.txt
tranquilizer-0.9.2.dist-info/top_level.txt
tranquilizer-0.9.2.dist-info/RECORD
