Metadata-Version: 2.1
Name: tranquilizer
Version: 0.9.2
Summary: Put your functions to REST
Home-page: https://github.com/AlbertDeFusco/tranquilizer
Author: Albert DeFusco
Author-email: albert.defusco@me.com
License: BSD 3-clause
Platform: Windows
Platform: Mac OS X
Platform: Linux
Classifier: Programming Language :: Python :: 3
Classifier: Programming Language :: Python :: 3.6
Classifier: Programming Language :: Python :: 3.7
Classifier: Programming Language :: Python :: 3.8
Classifier: Programming Language :: Python :: 3.9
Classifier: Programming Language :: Python :: 3.10
Classifier: Programming Language :: Python :: 3.11
Classifier: Programming Language :: Python :: 3.12
Classifier: License :: OSI Approved :: BSD License
Classifier: Framework :: Flask
Classifier: Operating System :: OS Independent
Classifier: Intended Audience :: Science/Research
Classifier: Intended Audience :: Developers
Classifier: Environment :: Web Environment
Requires-Python: >=3.6, <3.13
License-File: LICENSE
Requires-Dist: flask
Requires-Dist: werkzeug <2.1,>=0.15
Requires-Dist: flask-restx
Requires-Dist: flask-cors
Requires-Dist: python-dateutil
Requires-Dist: flask-jwt-extended >=4
Provides-Extra: all
Requires-Dist: ipython ; extra == 'all'
Requires-Dist: nbconvert ; extra == 'all'
Requires-Dist: numpy ; extra == 'all'
Requires-Dist: pillow ; extra == 'all'
Provides-Extra: recommended
Requires-Dist: nbconvert ; extra == 'recommended'
Requires-Dist: ipython ; extra == 'recommended'
Requires-Dist: numpy ; extra == 'recommended'
Requires-Dist: pillow ; extra == 'recommended'
